{"id": "l4-3-1", "level": 4, "module": 3, "lesson": 1, "title": "Kalınlaştırmaya Giriş", "description": "Taşları güçlendirme ve alan yaratma.", "duration_minutes": 10, "content": [{"type": "text", "content": "Kalınlaştırma (thickness), taşları güçlü hale getirme ve çevresindeki bölgeyi kontrol altına alma sanatıdır. Kalın taşlar saldırı için potansiyel enerji biriktirir - ama yanlış kalınlaştırma tempo kaybettirir."}, {"type": "board", "size": 9, "stones": [{"x": 3, "y": 3, "color": "black"}, {"x": 4, "y": 3, "color": "black"}, {"x": 3, "y": 4, "color": "black"}, {"x": 4, "y": 4, "color": "black"}], "highlights": [{"x": 5, "y": 3, "type": "bad"}], "annotation": "İdeal kalınlık: 2x2 blok - 4 yöne güçlü!"}, {"type": "text", "content": "Kalınlaştırma kuralları: 1) İdeal 2x2 veya 3x2 halka 2) Dışarıya açık olmalı 3) Merkeze yakın olmalı 4) Rakip tarafından kesilmemeli."}], "prerequisites": ["l4-2-4"], "next_lesson": "l4-3-2", "required_exercise": "e4-3-4"}
