{
  "id": "l6-3-1",
  "level": 6,
  "module": 3,
  "lesson": 1,
  "title": "Seten",
  "description": "Merkez kontrolü ve güç.",
  "duration_minutes": 10,
  "content": [
    {
      "type": "text",
      "content": "Seten: Merkez kontrolü ve güç. Temel kavramları ve stratejileri öğrenin."
    },
    {
      "type": "board",
      "size": 9,
      "stones": [
        {
          "x": 4,
          "y": 4,
          "color": "black"
        },
        {
          "x": 4,
          "y": 5,
          "color": "white"
        }
      ],
      "highlights": [],
      "annotation": "Seten"
    },
    {
      "type": "animation",
      "steps": [
        {
          "stones": [
            {
              "x": 4,
              "y": 4,
              "color": "black"
            }
          ],
          "text": "Pozisyon analizi başladı"
        },
        {
          "stones": [
            {
              "x": 4,
              "y": 4,
              "color": "black"
            },
            {
              "x": 4,
              "y": 5,
              "color": "white"
            }
          ],
          "text": "Taşlar yerleşti"
        },
        {
          "stones": [
            {
              "x": 4,
              "y": 4,
              "color": "black"
            },
            {
              "x": 4,
              "y": 5,
              "color": "white"
            },
            {
              "x": 5,
              "y": 4,
              "color": "black"
            }
          ],
          "text": "Sonraki hamleyi düşünün"
        }
      ]
    }
  ],
  "prerequisites": [
    "l6-2-4"
  ],
  "next_lesson": "l6-3-2",
  "required_exercise": "e6-3-1"
}