{
  "id": "e2-4-6",
  "level": 2,
  "module": 4,
  "lesson": 6,
  "type": "endgame",
  "title": "Yose Sırası",
  "description": "Doğru yose sırası.",
  "board_size": 9,
  "initial_stones": [
    {
      "x": 2,
      "y": 2,
      "color": "black"
    },
    {
      "x": 3,
      "y": 2,
      "color": "white"
    },
    {
      "x": 2,
      "y": 3,
      "color": "white"
    },
    {
      "x": 6,
      "y": 6,
      "color": "white"
    },
    {
      "x": 7,
      "y": 6,
      "color": "black"
    },
    {
      "x": 6,
      "y": 7,
      "color": "black"
    }
  ],
  "correct_moves": [
    {
      "x": 1,
      "y": 2,
      "is_correct": true,
      "explanation": "Büyük sente önce!"
    }
  ],
  "hints": [
    "Sente her zaman önce oynanmalı."
  ],
  "difficulty": 3,
  "stars_required": 1
}